wechat_sdk/__init__.py
wechat_sdk/cloudbase/__init__.py
wechat_sdk/cloudrun/__init__.py
wechat_sdk/cloudrun/config.py
wechat_sdk/cloudrun/settings.toml
wechat_sdk/cloudrun/api/__init__.py
wechat_sdk/cloudrun/api/pay.py
wechat_sdk/login/__init__.py
wechat_sdk/login/api.py
wechat_sdk/login/exception.py
wechat_sdk/login/model.py
wechat_sdk/pay/__init__.py
wechat_sdk/pay/base.py
wechat_sdk/pay/order.py
wechat_sdk/pay/sign.py
wechat_sdk/pay/utils.py
wechat_sdk_py-0.1.0a2.dist-info/LICENSE
wechat_sdk_py-0.1.0a2.dist-info/METADATA
wechat_sdk_py-0.1.0a2.dist-info/WHEEL
wechat_sdk_py-0.1.0a2.dist-info/top_level.txt
wechat_sdk_py-0.1.0a2.dist-info/RECORD
