Metadata-Version: 2.1
Name: wechat-sdk-py
Version: 0.1.0a2
Author-email: "QuantTide Inc." <opensource@quanttide.com>
License: Apache License
Classifier: Programming Language :: Python :: 3
Requires-Python: >=3
License-File: LICENSE
Requires-Dist: dynaconf
Requires-Dist: cryptography
Requires-Dist: requests
Provides-Extra: test
Requires-Dist: responses ; extra == 'test'
